{"struct":{"i":"id","n":"name"},"data":[{"i":"10034","n":"База Mагистраль 2"},{"i":"10044","n":"База Mагистраль 3"},{"i":"10045","n":"База Магистраль1"},{"i":"10038","n":"База Турне"},{"i":"10046","n":"Горящий"},{"i":"10039","n":"Друзья, родственники, знакомые"},{"i":"10053","n":"Импорт 21.07.2019 в 16:38"},{"i":"10256","n":"Коллеги и партнеры"},{"i":"10047","n":"Лиды Ogo.tours"},{"i":"10048","n":"Обращались,но не купили"},{"i":"10040","n":"Подписчики"},{"i":"10049","n":"Постоянный клиент"},{"i":"10041","n":"Прозвонщик"},{"i":"10042","n":"Работа - Строители (плиточник,штукатур,гипс,маляр)"},{"i":"10050","n":"С улицы"},{"i":"10051","n":"ТРУДОУСТРОЙСТВО"},{"i":"10043","n":"Турист (1 раз)"},{"i":"10052","n":"Холодные очень"}]}